Metadata-Version: 2.1
Name: tkinter-serial-monitor
Version: 1.0.0
Summary: a tkinter based gui Arduino serial monitor with graphing capabilites
Home-page: https://github.com/ryanGT/tkinter_serial_monitor
Author: Ryan Krauss
Author-email: ryanwkrauss@gmail.com
Classifier: Programming Language :: Python :: 3
Classifier: License :: OSI Approved :: MIT License
Classifier: Operating System :: OS Independent
